instel/__init__.py
instel/reason.py
instel-0.1.0.dist-info/METADATA
instel-0.1.0.dist-info/WHEEL
instel-0.1.0.dist-info/entry_points.txt
instel-0.1.0.dist-info/RECORD
