Metadata-Version: 2.4
Name: instel
Version: 0.1.0
Summary: Add your description here
Requires-Python: >=3.10
Requires-Dist: openai>=1.95.1
